persil/__init__.py
persil/generator.py
persil/parser.py
persil/parsers/__init__.py
persil/parsers/from_enum.py
persil/parsers/index.py
persil/parsers/outcome.py
persil/parsers/regex.py
persil/parsers/string.py
persil/parsers/tag.py
persil/py.typed
persil/result.py
persil/stream.py
persil/utils.py
persil-0.1.0.dist-info/LICENSE
persil-0.1.0.dist-info/METADATA
persil-0.1.0.dist-info/WHEEL
persil-0.1.0.dist-info/RECORD
