Metadata-Version: 2.1
Name: persil
Version: 0.1.0
Summary: Persil is a pure-python parsing library, inspired by Parsy
License: MIT
Author: Basile Dura
Author-email: basile@bdura.me
Requires-Python: >=3.10,<4.0
Classifier: License :: OSI Approved :: MIT License
Classifier: Programming Language :: Python :: 3
Classifier: Programming Language :: Python :: 3.10
Classifier: Programming Language :: Python :: 3.11
Classifier: Programming Language :: Python :: 3.12
